{
  "$schema": "http://json-schema.org/draft-07/schema#",
  "title": "InstantiateMsg",
  "type": "object",
  "required": [
    "app_components",
    "kernel_address",
    "name"
  ],
  "properties": {
    "app_components": {
      "type": "array",
      "items": {
        "$ref": "#/definitions/AppComponent"
      }
    },
    "chain_info": {
      "type": [
        "array",
        "null"
      ],
      "items": {
        "$ref": "#/definitions/ChainInfo"
      }
    },
    "kernel_address": {
      "type": "string"
    },
    "name": {
      "type": "string"
    },
    "owner": {
      "type": [
        "string",
        "null"
      ]
    }
  },
  "additionalProperties": false,
  "definitions": {
    "AndrAddr": {
      "description": "An address that can be used within the Andromeda ecosystem. Inspired by the cosmwasm-std `Addr` type. https://github.com/CosmWasm/cosmwasm/blob/2a1c698520a1aacedfe3f4803b0d7d653892217a/packages/std/src/addresses.rs#L33\n\nThis address can be one of two things: 1. A valid human readable address e.g. `cosmos1...` 2. A valid Andromeda VFS path e.g. `/home/user/app/component`\n\nVFS paths can be local in the case of an app and can be done by referencing `./component` they can also contain protocols for cross chain communication. A VFS path is usually structured as so:\n\n`<protocol>://<chain (required if ibc used)>/<path>` or `ibc://cosmoshub-4/user/app/component`",
      "type": "string",
      "pattern": "(^((([A-Za-z0-9]+://)?([A-Za-z0-9.\\-_]{2,40}/)))?((~[a-z0-9]{2,}|(lib|home))(/[A-Za-z0-9.\\-_]{2,40}?)*(/)?)$)|(^(~[a-z0-9]{2,}|/(lib|home))(/[A-Za-z0-9.\\-_]{2,40}?)*(/)?$)|(^[a-z0-9]{2,}$)|(^\\.(/[A-Za-z0-9.\\-_]{2,40}?)*(/)?$)"
    },
    "AppComponent": {
      "type": "object",
      "required": [
        "ado_type",
        "component_type",
        "name"
      ],
      "properties": {
        "ado_type": {
          "type": "string"
        },
        "component_type": {
          "$ref": "#/definitions/ComponentType"
        },
        "name": {
          "type": "string"
        }
      },
      "additionalProperties": false
    },
    "Binary": {
      "description": "Binary is a wrapper around Vec<u8> to add base64 de/serialization with serde. It also adds some helper methods to help encode inline.\n\nThis is only needed as serde-json-{core,wasm} has a horrible encoding for Vec<u8>. See also <https://github.com/CosmWasm/cosmwasm/blob/main/docs/MESSAGE_TYPES.md>.",
      "type": "string"
    },
    "ChainInfo": {
      "type": "object",
      "required": [
        "chain_name",
        "owner"
      ],
      "properties": {
        "chain_name": {
          "type": "string"
        },
        "owner": {
          "type": "string"
        }
      },
      "additionalProperties": false
    },
    "ComponentType": {
      "oneOf": [
        {
          "type": "object",
          "required": [
            "new"
          ],
          "properties": {
            "new": {
              "$ref": "#/definitions/Binary"
            }
          },
          "additionalProperties": false
        },
        {
          "type": "object",
          "required": [
            "symlink"
          ],
          "properties": {
            "symlink": {
              "$ref": "#/definitions/AndrAddr"
            }
          },
          "additionalProperties": false
        },
        {
          "type": "object",
          "required": [
            "cross_chain"
          ],
          "properties": {
            "cross_chain": {
              "$ref": "#/definitions/CrossChainComponent"
            }
          },
          "additionalProperties": false
        }
      ]
    },
    "CrossChainComponent": {
      "type": "object",
      "required": [
        "chain",
        "instantiate_msg"
      ],
      "properties": {
        "chain": {
          "type": "string"
        },
        "instantiate_msg": {
          "$ref": "#/definitions/Binary"
        }
      },
      "additionalProperties": false
    }
  }
}
