{
  "$schema": "http://json-schema.org/draft-07/schema#",
  "title": "QueryMsg",
  "oneOf": [
    {
      "type": "object",
      "required": [
        "state"
      ],
      "properties": {
        "state": {
          "type": "object",
          "additionalProperties": false
        }
      },
      "additionalProperties": false
    },
    {
      "type": "object",
      "required": [
        "config"
      ],
      "properties": {
        "config": {
          "type": "object",
          "additionalProperties": false
        }
      },
      "additionalProperties": false
    },
    {
      "type": "object",
      "required": [
        "available_tokens"
      ],
      "properties": {
        "available_tokens": {
          "type": "object",
          "properties": {
            "limit": {
              "type": [
                "integer",
                "null"
              ],
              "format": "uint32",
              "minimum": 0.0
            },
            "start_after": {
              "type": [
                "string",
                "null"
              ]
            }
          },
          "additionalProperties": false
        }
      },
      "additionalProperties": false
    },
    {
      "type": "object",
      "required": [
        "is_token_available"
      ],
      "properties": {
        "is_token_available": {
          "type": "object",
          "required": [
            "id"
          ],
          "properties": {
            "id": {
              "type": "string"
            }
          },
          "additionalProperties": false
        }
      },
      "additionalProperties": false
    },
    {
      "type": "object",
      "required": [
        "owner"
      ],
      "properties": {
        "owner": {
          "type": "object",
          "additionalProperties": false
        }
      },
      "additionalProperties": false
    },
    {
      "type": "object",
      "required": [
        "operators"
      ],
      "properties": {
        "operators": {
          "type": "object",
          "additionalProperties": false
        }
      },
      "additionalProperties": false
    },
    {
      "type": "object",
      "required": [
        "type"
      ],
      "properties": {
        "type": {
          "type": "object",
          "additionalProperties": false
        }
      },
      "additionalProperties": false
    },
    {
      "type": "object",
      "required": [
        "kernel_address"
      ],
      "properties": {
        "kernel_address": {
          "type": "object",
          "additionalProperties": false
        }
      },
      "additionalProperties": false
    },
    {
      "type": "object",
      "required": [
        "original_publisher"
      ],
      "properties": {
        "original_publisher": {
          "type": "object",
          "additionalProperties": false
        }
      },
      "additionalProperties": false
    },
    {
      "type": "object",
      "required": [
        "block_height_upon_creation"
      ],
      "properties": {
        "block_height_upon_creation": {
          "type": "object",
          "additionalProperties": false
        }
      },
      "additionalProperties": false
    },
    {
      "type": "object",
      "required": [
        "is_operator"
      ],
      "properties": {
        "is_operator": {
          "type": "object",
          "required": [
            "address"
          ],
          "properties": {
            "address": {
              "type": "string"
            }
          },
          "additionalProperties": false
        }
      },
      "additionalProperties": false
    },
    {
      "type": "object",
      "required": [
        "version"
      ],
      "properties": {
        "version": {
          "type": "object",
          "additionalProperties": false
        }
      },
      "additionalProperties": false
    }
  ]
}
